aima_toolkit/__init__.py
aima_toolkit/ConstraintSatisfactionProblemPackage/__init__.py
aima_toolkit/ConstraintSatisfactionProblemPackage/constraint_satisfaction_problem.py
aima_toolkit/ConstraintSatisfactionProblemPackage/ConstraintPropagation/__init__.py
aima_toolkit/ConstraintSatisfactionProblemPackage/ConstraintPropagation/ac3_propagation.py
aima_toolkit/ConstraintSatisfactionProblemPackage/ConstraintPropagation/node_constraint_propagation.py
aima_toolkit/ConstraintSatisfactionProblemPackage/PremadeConstraints/__init__.py
aima_toolkit/ConstraintSatisfactionProblemPackage/PremadeConstraints/alldiff_constraint.py
aima_toolkit/ConstraintSatisfactionProblemPackage/Search/__init__.py
aima_toolkit/ConstraintSatisfactionProblemPackage/Search/backtracking_search.py
aima_toolkit/ConstraintSatisfactionProblemPackage/Search/search_inference.py
aima_toolkit/ConstraintSatisfactionProblemPackage/Search/value_selection.py
aima_toolkit/ConstraintSatisfactionProblemPackage/Search/variable_selection.py
aima_toolkit/Problems/__init__.py
aima_toolkit/Problems/eight_queen_problem.py
aima_toolkit/Problems/erratic_vacuum_world.py
aima_toolkit/Problems/find_the_ip_phone.py
aima_toolkit/Problems/online_corridor_problem.py
aima_toolkit/Problems/partially_observable_vacuum_world.py
aima_toolkit/Problems/romania_search_problem.py
aima_toolkit/Problems/sensorless_vacuum_world.py
aima_toolkit/Problems/simple_tree_search_problem.py
aima_toolkit/Problems/vacuum_world.py
aima_toolkit/Sampling/__init__.py
aima_toolkit/Sampling/reservoir_sample.py
aima_toolkit/SearchProblemPackage/__init__.py
aima_toolkit/SearchProblemPackage/expand.py
aima_toolkit/SearchProblemPackage/node.py
aima_toolkit/SearchProblemPackage/queue.py
aima_toolkit/SearchProblemPackage/searchproblem.py
aima_toolkit/SearchProblemPackage/SearchAlgorithms/__init__.py
aima_toolkit/SearchProblemPackage/SearchAlgorithms/InformedSearch/__init__.py
aima_toolkit/SearchProblemPackage/SearchAlgorithms/InformedSearch/a_star_search.py
aima_toolkit-2.1.2.dist-info/METADATA
aima_toolkit-2.1.2.dist-info/WHEEL
aima_toolkit-2.1.2.dist-info/licenses/LICENSE
aima_toolkit-2.1.2.dist-info/RECORD
