Metadata-Version: 2.4
Name: aima_toolkit
Version: 2.1.2
Summary: I made this package to help me on my learning journey through the AIMA book and contains all algorithms I build whilst learning through the book
Project-URL: Homepage, https://github.com/EmreArapcicUevak/aima-toolkit
Project-URL: Issues, https://github.com/EmreArapcicUevak/aima-toolkit/issues
Author-email: Emre Arapcic-Uevak <emrearapcicuevak@gmail.com>
License-Expression: MIT
License-File: LICENSE
Classifier: Operating System :: OS Independent
Classifier: Programming Language :: Python :: 3
Requires-Python: >=3.9
Provides-Extra: dev
Requires-Dist: pytest>=8.4.1; extra == 'dev'
